{
    "version": 3,
    "templateParts": [
        {
            "name": "header",
            "area": "header",
            "title": "Header"
        },
        {
            "name": "footer",
            "area": "footer",
            "title": "Footer"
        }
    ],
    "customTemplates": [
        {
            "name": "page-about-us",
            "title": "About us page",
            "postTypes": [ "page", "post" ]
        }
    ],
    "settings": {
        "color": {
            "palette": [
                {
                    "slug": "primary",
                    "color": "#116020",
                    "name": "Main Palette"
                },
                {
                    "slug": "secondary",
                    "color": "#22aa60",
                    "name": "Secondary Palette"
                }
            ],
            "gradients": [
                {
                    "slug": "primary-to-secondary",
                    "gradient": "linear-gradient(0deg, var(--wp--preset--color--primary), var(--wp--preset--color--secondary))",
                    "name": "Priamry to Secondary"
                }
            
            ],
            "dutone": [
            
            ]
        },
        "typography": {
            "fontFamilies": [ 
                {
                    "fontFamily": "Arial, sans-serif",
                    "slug": "generic-font-family",
                    "name" : "Generic Font Family"
                }
            ]
        },
        "layout": {
            "contentSize": "1000px",
            "wideSize": "1500px"
            
        },
        "spacing": {
            "padding": "true",
            "margin": "true",
            "units": "px, em, rem"
        },
        "border": {
            "width": true,
            "style": true,
            "color": true,
            "radius": true            
        },
        "blocks": {
            "core/heading": {
                "slug": "tertiary",
                "color": "#00cc00",
                "name": "Tertiary"
                
            }
        }
    },
    "custom": {
       "spacing": "10px",
       "extra-spacing": "20px"
    },
    "styles": {},
    "custom-templates": [],
    "templateParts": [] 
}
